Juneja/__init__.py
Juneja-1.0.dist-info/License.txt
Juneja-1.0.dist-info/METADATA
Juneja-1.0.dist-info/WHEEL
Juneja-1.0.dist-info/top_level.txt
Juneja-1.0.dist-info/RECORD
