Metadata-Version: 2.1
Name: Juneja
Version: 1.0
Summary: This is a Python Module made by Ansh Juneja
Home-page: UNKNOWN
Author: Ansh Juneja
Author-email: ansh.63@live.com
License: UNKNOWN
Platform: UNKNOWN
License-File: License.txt
